<?xml version="1.0" encoding="utf-8" ?>
<Defs>

	<TeleCore.NetworkDef>
		<defName>AtmosphericNetwork</defName>
		<containerLabel>Atmospheres</containerLabel>
		<transmitterDef>AtmosphericPipe</transmitterDef>
		<controllerDef>AtmosphericController</controllerDef>
		<transmitterGraphic>
			<texPath>Buildings/Network/Pipe_Air</texPath>
			<graphicClass>Graphic_Single</graphicClass>
		</transmitterGraphic>
		<overlayGraphic>
			<texPath>Buildings/Network/Pipe_Air_overlay</texPath>
			<graphicClass>Graphic_Single</graphicClass>
			<shaderType>MetaOverlay</shaderType>
			<color>(140, 230, 255)</color>
		</overlayGraphic>
	</TeleCore.NetworkDef>
	
</Defs>
